intek/__init__.py
intek/application/__init__.py
intek/application/etl.py
intek/application/geocoding.py
intek/application/model.py
intek/application/templates/20200525 - Ultime relance cash.pdf
intek/application/templates/20200702 - Paiement ete 2020.pdf
intek/application/templates/eng.html
intek/application/templates/eng.jpg
intek/application/templates/fra.html
intek/application/templates/fra.jpg
intek/application/templates/instructions.jpg
intek/application/templates/vie.html
intek/application/templates/vie.jpeg
school_transport_application_form_tool-1.2.15.data/scripts/process_applications
school_transport_application_form_tool-1.2.15.dist-info/METADATA
school_transport_application_form_tool-1.2.15.dist-info/WHEEL
school_transport_application_form_tool-1.2.15.dist-info/top_level.txt
school_transport_application_form_tool-1.2.15.dist-info/RECORD
