Metadata-Version: 2.1
Name: school-transport-application-form-tool
Version: 1.2.15
Summary: School Transport Application Form Tool
Home-page: https://github.com/dcaune/school-transport-application-form-tool
Author: Daniel CAUNE
Author-email: daniel.caune@gmail.com
License: MIT
Project-URL: Bug Tracker, https://github.com/dcaune/school-transport-application-form-tool/issues
Project-URL: Documentation, https://github.com/dcaune/school-transport-application-form-tool
Project-URL: Source Code, https://github.com/dcaune/school-transport-application-form-tool
Platform: any
Classifier: Development Status :: 5 - Production/Stable
Classifier: License :: OSI Approved :: MIT License
Classifier: Operating System :: OS Independent
Classifier: Programming Language :: Python
Classifier: Topic :: Software Development :: Libraries
Requires-Python: >=3.6
Requires-Dist: unidecode
Requires-Dist: perseus-core-library
Requires-Dist: wheel
Requires-Dist: setuptools
Requires-Dist: twine
Requires-Dist: oauth2client
Requires-Dist: google-api-python-client
Requires-Dist: google-auth-httplib2
Requires-Dist: google-auth-oauthlib
Requires-Dist: langdetect
Requires-Dist: requests
Requires-Dist: perseus-place-core-library
